fm/templatetags
fm
