Metadata-Version: 1.1
Name: django-fm
Version: 0.2.5
Summary: Twitter Bootstrap 3 based modal AJAX form for Django
Home-page: https://github.com/FZambia/django-fm/
Author: Alexandr Emelin <frvzmb@gmail.com>
Author-email: frvzmb@gmail.com
License: MIT
Keywords: django,views,forms,ajax,bootstrap,modal,create,update,delete
Platform: UNKNOWN
Classifier: Programming Language :: Python
Classifier: Topic :: Software Development :: Libraries :: Python Modules
Classifier: Framework :: Django
Classifier: Environment :: Web Environment
Classifier: Development Status :: 4 - Beta
Classifier: Programming Language :: Python :: 2.6
Classifier: Programming Language :: Python :: 2.7
Classifier: Programming Language :: Python :: 3.3
Classifier: Programming Language :: Python :: 3.4
